source_typeform/__init__.py
source_typeform/components.py
source_typeform/manifest.yaml
source_typeform/run.py
source_typeform/source.py
airbyte_source_typeform-1.3.27.dist-info/METADATA
airbyte_source_typeform-1.3.27.dist-info/WHEEL
airbyte_source_typeform-1.3.27.dist-info/entry_points.txt
airbyte_source_typeform-1.3.27.dist-info/RECORD
